[
    {
        "id": 1,
        "first_name": "Madonna",
        "last_name": "Beebis",
        "age": 53,
        "gender": "Female",
        "adress": "502 Division Court",
        "adressSecondLine": "Room 576",
        "email": "mbeebis0@aboutads.info",
        "phone": "+86 899 143 1182",
        "notes": "mbeebis0@seattletimes.com",
        "employmentStatus": "Budget/Accounting Analyst IV",
        "job": "Electrical Engineer",
        "creditScore": 330,
        "annualIncome": "€82649,55",
        "estimatedExpanses": "€3011,03",
        "netMonthlyIncome": "€70825,79",
        "reserves": "€206532,24"
    },
    {
        "id": 2,
        "first_name": "Vinnie",
        "last_name": "Cobelli",
        "age": 34,
        "gender": "Male",
        "adress": "6 Hoard Terrace",
        "adressSecondLine": "Apt 1779",
        "email": "vcobelli1@facebook.com",
        "phone": "+86 878 440 5333",
        "notes": "vcobelli1@tripod.com",
        "employmentStatus": "Marketing Manager",
        "job": "Account Coordinator",
        "creditScore": 569,
        "annualIncome": "€75834,91",
        "estimatedExpanses": "€3625,67",
        "netMonthlyIncome": "€1904,48",
        "reserves": "€85166,93"
    },
    {
        "id": 3,
        "first_name": "Pall",
        "last_name": "Pettis",
        "age": 36,
        "gender": "Male",
        "adress": "9 Stephen Street",
        "adressSecondLine": "Apt 1972",
        "email": "ppettis2@hatena.ne.jp",
        "phone": "+353 670 564 8541",
        "notes": "ppettis2@macromedia.com",
        "employmentStatus": "Junior Executive",
        "job": "Director of Sales",
        "creditScore": 792,
        "annualIncome": "€68964,99",
        "estimatedExpanses": "€2652,97",
        "netMonthlyIncome": "€39734,77",
        "reserves": "€162401,40"
    },
    {
        "id": 4,
        "first_name": "Johnnie",
        "last_name": "Dunkerley",
        "age": 67,
        "gender": "Male",
        "adress": "43417 Crowley Plaza",
        "adressSecondLine": "Room 97",
        "email": "jdunkerley3@usnews.com",
        "phone": "+55 352 513 0222",
        "notes": "jdunkerley3@whitehouse.gov",
        "employmentStatus": "Chief Design Engineer",
        "job": "Environmental Tech",
        "creditScore": 545,
        "annualIncome": "€73150,38",
        "estimatedExpanses": "€1674,07",
        "netMonthlyIncome": "€50105,42",
        "reserves": "€171979,63"
    },
    {
        "id": 5,
        "first_name": "Roselin",
        "last_name": "Masarrat",
        "age": 28,
        "gender": "Female",
        "adress": "3075 Schmedeman Court",
        "adressSecondLine": "Suite 79",
        "email": "rmasarrat4@wufoo.com",
        "phone": "+84 318 316 3527",
        "notes": "rmasarrat4@icq.com",
        "employmentStatus": "Administrative Officer",
        "job": "Librarian",
        "creditScore": 453,
        "annualIncome": "€85453,24",
        "estimatedExpanses": "€2258,21",
        "netMonthlyIncome": "€43398,67",
        "reserves": "€276559,80"
    },
    {
        "id": 6,
        "first_name": "Magdaia",
        "last_name": "Hatto",
        "age": 64,
        "gender": "Female",
        "adress": "6910 Texas Point",
        "adressSecondLine": "Room 336",
        "email": "mhatto5@accuweather.com",
        "phone": "+84 970 524 7680",
        "notes": "mhatto5@google.es",
        "employmentStatus": "Teacher",
        "job": "Software Engineer II",
        "creditScore": 514,
        "annualIncome": "€30772,82",
        "estimatedExpanses": "€2581,90",
        "netMonthlyIncome": "€65955,99",
        "reserves": "€261658,83"
    },
    {
        "id": 7,
        "first_name": "Jeffrey",
        "last_name": "Goatcher",
        "age": 38,
        "gender": "Male",
        "adress": "5368 Memorial Alley",
        "adressSecondLine": "Suite 71",
        "email": "jgoatcher6@joomla.org",
        "phone": "+86 422 103 0993",
        "notes": "jgoatcher6@cafepress.com",
        "employmentStatus": "General Manager",
        "job": "Executive Secretary",
        "creditScore": 338,
        "annualIncome": "€77862,95",
        "estimatedExpanses": "€3812,91",
        "netMonthlyIncome": "€50447,38",
        "reserves": "€104024,93"
    },
    {
        "id": 8,
        "first_name": "Chucho",
        "last_name": "MacPhee",
        "age": 35,
        "gender": "Male",
        "adress": "13 Morning Plaza",
        "adressSecondLine": "17th Floor",
        "email": "cmacphee7@instagram.com",
        "phone": "+62 292 525 4622",
        "notes": "cmacphee7@github.io",
        "employmentStatus": "Actuary",
        "job": "Registered Nurse",
        "creditScore": 387,
        "annualIncome": "€98801,50",
        "estimatedExpanses": "€3587,05",
        "netMonthlyIncome": "€61576,37",
        "reserves": "€156899,49"
    },
    {
        "id": 9,
        "first_name": "Desmund",
        "last_name": "Malin",
        "age": 51,
        "gender": "Male",
        "adress": "6 Esch Avenue",
        "adressSecondLine": "Room 194",
        "email": "dmalin8@independent.co.uk",
        "phone": "+380 152 627 3629",
        "notes": "dmalin8@arstechnica.com",
        "employmentStatus": "Design Engineer",
        "job": "Community Outreach Specialist",
        "creditScore": 370,
        "annualIncome": "€44464,85",
        "estimatedExpanses": "€3697,46",
        "netMonthlyIncome": "€31730,34",
        "reserves": "€115266,39"
    },
    {
        "id": 10,
        "first_name": "Rand",
        "last_name": "Defraine",
        "age": 36,
        "gender": "Male",
        "adress": "22321 Elgar Pass",
        "adressSecondLine": "Apt 422",
        "email": "rdefraine9@storify.com",
        "phone": "+48 175 669 7225",
        "notes": "rdefraine9@ucla.edu",
        "employmentStatus": "Geological Engineer",
        "job": "Operator",
        "creditScore": 527,
        "annualIncome": "€75515,52",
        "estimatedExpanses": "€2204,80",
        "netMonthlyIncome": "€5381,38",
        "reserves": "€115155,34"
    },
    {
        "id": 11,
        "first_name": "Moll",
        "last_name": "Branscombe",
        "age": 25,
        "gender": "Female",
        "adress": "4899 Glendale Alley",
        "adressSecondLine": "Room 293",
        "email": "mbranscombea@arizona.edu",
        "phone": "+46 385 950 2933",
        "notes": "mbranscombea@wiley.com",
        "employmentStatus": "Operator",
        "job": "Legal Assistant",
        "creditScore": 554,
        "annualIncome": "€75736,06",
        "estimatedExpanses": "€2104,44",
        "netMonthlyIncome": "€7597,52",
        "reserves": "€47857,75"
    },
    {
        "id": 12,
        "first_name": "Marv",
        "last_name": "Jerdon",
        "age": 54,
        "gender": "Male",
        "adress": "9 Fulton Avenue",
        "adressSecondLine": "Apt 1768",
        "email": "mjerdonb@un.org",
        "phone": "+52 242 737 8220",
        "notes": "mjerdonb@amazon.co.jp",
        "employmentStatus": "Biostatistician IV",
        "job": "Account Representative III",
        "creditScore": 395,
        "annualIncome": "€31819,74",
        "estimatedExpanses": "€2800,22",
        "netMonthlyIncome": "€32143,20",
        "reserves": "€123022,47"
    },
    {
        "id": 13,
        "first_name": "Celestyn",
        "last_name": "Ricardet",
        "age": 42,
        "gender": "Female",
        "adress": "1 Esker Park",
        "adressSecondLine": "Apt 660",
        "email": "cricardetc@sfgate.com",
        "phone": "+62 508 351 4450",
        "notes": "cricardetc@walmart.com",
        "employmentStatus": "Mechanical Systems Engineer",
        "job": "Actuary",
        "creditScore": 453,
        "annualIncome": "€52118,37",
        "estimatedExpanses": "€2395,44",
        "netMonthlyIncome": "€58102,57",
        "reserves": "€164145,00"
    },
    {
        "id": 14,
        "first_name": "Gerry",
        "last_name": "Wynrahame",
        "age": 26,
        "gender": "Male",
        "adress": "84744 Independence Plaza",
        "adressSecondLine": "Suite 93",
        "email": "gwynrahamed@people.com.cn",
        "phone": "+62 924 616 6200",
        "notes": "gwynrahamed@telegraph.co.uk",
        "employmentStatus": "Quality Engineer",
        "job": "Account Coordinator",
        "creditScore": 433,
        "annualIncome": "€40476,54",
        "estimatedExpanses": "€2157,32",
        "netMonthlyIncome": "€8425,29",
        "reserves": "€135913,36"
    },
    {
        "id": 15,
        "first_name": "Merna",
        "last_name": "Sproat",
        "age": 56,
        "gender": "Female",
        "adress": "21 Muir Plaza",
        "adressSecondLine": "PO Box 75195",
        "email": "msproate@telegraph.co.uk",
        "phone": "+95 637 989 4297",
        "notes": "msproate@cnbc.com",
        "employmentStatus": "Computer Systems Analyst I",
        "job": "Software Test Engineer II",
        "creditScore": 476,
        "annualIncome": "€103299,02",
        "estimatedExpanses": "€3128,87",
        "netMonthlyIncome": "€50428,47",
        "reserves": "€87516,52"
    },
    {
        "id": 16,
        "first_name": "Kelly",
        "last_name": "Brennenstuhl",
        "age": 37,
        "gender": "Male",
        "adress": "226 Harper Alley",
        "adressSecondLine": "PO Box 12892",
        "email": "kbrennenstuhlf@wufoo.com",
        "phone": "+1 619 307 8882",
        "notes": "kbrennenstuhlf@cafepress.com",
        "employmentStatus": "Social Worker",
        "job": "Desktop Support Technician",
        "creditScore": 890,
        "annualIncome": "€97430,37",
        "estimatedExpanses": "€3053,16",
        "netMonthlyIncome": "€28577,98",
        "reserves": "€77535,12"
    },
    {
        "id": 17,
        "first_name": "Bear",
        "last_name": "Bingley",
        "age": 61,
        "gender": "Male",
        "adress": "19817 Carberry Pass",
        "adressSecondLine": "Suite 68",
        "email": "bbingleyg@feedburner.com",
        "phone": "+81 143 131 9054",
        "notes": "bbingleyg@google.com.br",
        "employmentStatus": "VP Sales",
        "job": "Registered Nurse",
        "creditScore": 716,
        "annualIncome": "€92725,09",
        "estimatedExpanses": "€2404,41",
        "netMonthlyIncome": "€50362,79",
        "reserves": "€46076,64"
    },
    {
        "id": 18,
        "first_name": "Ly",
        "last_name": "Bakey",
        "age": 50,
        "gender": "Male",
        "adress": "0 Lawn Street",
        "adressSecondLine": "Apt 1277",
        "email": "lbakeyh@de.vu",
        "phone": "+55 770 649 1129",
        "notes": "lbakeyh@usgs.gov",
        "employmentStatus": "Research Assistant IV",
        "job": "Developer IV",
        "creditScore": 675,
        "annualIncome": "€79056,06",
        "estimatedExpanses": "€3232,13",
        "netMonthlyIncome": "€54686,91",
        "reserves": "€206812,70"
    },
    {
        "id": 19,
        "first_name": "Hamlen",
        "last_name": "Riccardi",
        "age": 49,
        "gender": "Male",
        "adress": "20 Cambridge Street",
        "adressSecondLine": "Suite 20",
        "email": "hriccardii@usnews.com",
        "phone": "+62 630 679 3150",
        "notes": "hriccardii@moonfruit.com",
        "employmentStatus": "Environmental Specialist",
        "job": "Associate Professor",
        "creditScore": 664,
        "annualIncome": "€28406,32",
        "estimatedExpanses": "€1848,42",
        "netMonthlyIncome": "€56420,75",
        "reserves": "€57004,06"
    },
    {
        "id": 20,
        "first_name": "Prudence",
        "last_name": "Gillespey",
        "age": 43,
        "gender": "Female",
        "adress": "737 Dapin Circle",
        "adressSecondLine": "PO Box 44496",
        "email": "pgillespeyj@surveymonkey.com",
        "phone": "+386 907 787 0527",
        "notes": "pgillespeyj@google.de",
        "employmentStatus": "Payment Adjustment Coordinator",
        "job": "Tax Accountant",
        "creditScore": 736,
        "annualIncome": "€62565,99",
        "estimatedExpanses": "€1618,29",
        "netMonthlyIncome": "€1812,47",
        "reserves": "€275026,70"
    },
    {
        "id": 21,
        "first_name": "Zaria",
        "last_name": "Borthwick",
        "age": 29,
        "gender": "Female",
        "adress": "089 Everett Crossing",
        "adressSecondLine": "Room 130",
        "email": "zborthwickk@indiatimes.com",
        "phone": "+51 692 321 9492",
        "notes": "zborthwickk@github.com",
        "employmentStatus": "Actuary",
        "job": "Nurse",
        "creditScore": 379,
        "annualIncome": "€53364,70",
        "estimatedExpanses": "€2265,28",
        "netMonthlyIncome": "€44242,07",
        "reserves": "€157730,08"
    },
    {
        "id": 22,
        "first_name": "Hersh",
        "last_name": "Abramchik",
        "age": 68,
        "gender": "Male",
        "adress": "352 Maryland Pass",
        "adressSecondLine": "17th Floor",
        "email": "habramchikl@state.tx.us",
        "phone": "+33 813 212 6478",
        "notes": "habramchikl@ucoz.ru",
        "employmentStatus": "Environmental Specialist",
        "job": "Editor",
        "creditScore": 331,
        "annualIncome": "€91544,50",
        "estimatedExpanses": "€1881,84",
        "netMonthlyIncome": "€58762,11",
        "reserves": "€198314,19"
    },
    {
        "id": 23,
        "first_name": "Dynah",
        "last_name": "Pilbeam",
        "age": 19,
        "gender": "Female",
        "adress": "700 Paget Terrace",
        "adressSecondLine": "12th Floor",
        "email": "dpilbeamm@vistaprint.com",
        "phone": "+680 357 231 3676",
        "notes": "dpilbeamm@nydailynews.com",
        "employmentStatus": "Staff Scientist",
        "job": "Structural Engineer",
        "creditScore": 898,
        "annualIncome": "€110034,74",
        "estimatedExpanses": "€2413,27",
        "netMonthlyIncome": "€19479,93",
        "reserves": "€55717,92"
    },
    {
        "id": 24,
        "first_name": "Garreth",
        "last_name": "Gumb",
        "age": 37,
        "gender": "Male",
        "adress": "43821 David Lane",
        "adressSecondLine": "Suite 89",
        "email": "ggumbn@bbb.org",
        "phone": "+55 514 638 1377",
        "notes": "ggumbn@elegantthemes.com",
        "employmentStatus": "Editor",
        "job": "Web Developer IV",
        "creditScore": 304,
        "annualIncome": "€67890,47",
        "estimatedExpanses": "€3814,04",
        "netMonthlyIncome": "€57221,10",
        "reserves": "€167572,14"
    },
    {
        "id": 25,
        "first_name": "Trudy",
        "last_name": "Dericut",
        "age": 60,
        "gender": "Female",
        "adress": "64454 Corben Way",
        "adressSecondLine": "Room 1351",
        "email": "tdericuto@dropbox.com",
        "phone": "+62 959 497 3878",
        "notes": "tdericuto@prnewswire.com",
        "employmentStatus": "Project Manager",
        "job": "Database Administrator IV",
        "creditScore": 609,
        "annualIncome": "€89757,25",
        "estimatedExpanses": "€2956,71",
        "netMonthlyIncome": "€15671,67",
        "reserves": "€9648,43"
    },
    {
        "id": 26,
        "first_name": "Massimo",
        "last_name": "Bispham",
        "age": 34,
        "gender": "Male",
        "adress": "4685 8th Trail",
        "adressSecondLine": "Suite 100",
        "email": "mbisphamp@youtube.com",
        "phone": "+63 155 835 7855",
        "notes": "mbisphamp@cbsnews.com",
        "employmentStatus": "Accounting Assistant III",
        "job": "Software Consultant",
        "creditScore": 710,
        "annualIncome": "€117985,77",
        "estimatedExpanses": "€3998,28",
        "netMonthlyIncome": "€6800,74",
        "reserves": "€85205,07"
    },
    {
        "id": 27,
        "first_name": "Viki",
        "last_name": "Semper",
        "age": 64,
        "gender": "Female",
        "adress": "75640 Superior Park",
        "adressSecondLine": "Suite 25",
        "email": "vsemperq@alibaba.com",
        "phone": "+48 371 334 3514",
        "notes": "vsemperq@dedecms.com",
        "employmentStatus": "Sales Associate",
        "job": "Software Engineer IV",
        "creditScore": 349,
        "annualIncome": "€57288,28",
        "estimatedExpanses": "€3744,06",
        "netMonthlyIncome": "€12877,02",
        "reserves": "€264606,32"
    },
    {
        "id": 28,
        "first_name": "Weidar",
        "last_name": "Mignot",
        "age": 18,
        "gender": "Male",
        "adress": "808 Thompson Circle",
        "adressSecondLine": "Apt 325",
        "email": "wmignotr@usa.gov",
        "phone": "+353 913 219 6501",
        "notes": "wmignotr@canalblog.com",
        "employmentStatus": "Product Engineer",
        "job": "Social Worker",
        "creditScore": 570,
        "annualIncome": "€35260,08",
        "estimatedExpanses": "€1885,67",
        "netMonthlyIncome": "€63280,99",
        "reserves": "€292288,54"
    },
    {
        "id": 29,
        "first_name": "Brendon",
        "last_name": "Quilligan",
        "age": 65,
        "gender": "Male",
        "adress": "49 Shelley Center",
        "adressSecondLine": "13th Floor",
        "email": "bquilligans@berkeley.edu",
        "phone": "+55 362 355 0285",
        "notes": "bquilligans@technorati.com",
        "employmentStatus": "Human Resources Manager",
        "job": "Programmer II",
        "creditScore": 590,
        "annualIncome": "€29036,83",
        "estimatedExpanses": "€3730,33",
        "netMonthlyIncome": "€33743,16",
        "reserves": "€83658,60"
    },
    {
        "id": 30,
        "first_name": "Sherry",
        "last_name": "Hince",
        "age": 57,
        "gender": "Female",
        "adress": "081 Lien Circle",
        "adressSecondLine": "Room 1697",
        "email": "shincet@geocities.com",
        "phone": "+506 244 358 7323",
        "notes": "shincet@histats.com",
        "employmentStatus": "Civil Engineer",
        "job": "Senior Financial Analyst",
        "creditScore": 779,
        "annualIncome": "€52186,01",
        "estimatedExpanses": "€2609,17",
        "netMonthlyIncome": "€55068,87",
        "reserves": "€160340,55"
    },
    {
        "id": 31,
        "first_name": "Giffard",
        "last_name": "Snoxell",
        "age": 45,
        "gender": "Male",
        "adress": "3005 Sunbrook Place",
        "adressSecondLine": "PO Box 56711",
        "email": "gsnoxellu@house.gov",
        "phone": "+234 918 411 6376",
        "notes": "gsnoxellu@intel.com",
        "employmentStatus": "Electrical Engineer",
        "job": "Editor",
        "creditScore": 728,
        "annualIncome": "€82797,80",
        "estimatedExpanses": "€2992,81",
        "netMonthlyIncome": "€37042,32",
        "reserves": "€63199,78"
    },
    {
        "id": 32,
        "first_name": "Joyann",
        "last_name": "Ormshaw",
        "age": 69,
        "gender": "Female",
        "adress": "5765 Old Gate Way",
        "adressSecondLine": "Apt 521",
        "email": "jormshawv@shop-pro.jp",
        "phone": "+7 988 291 3378",
        "notes": "jormshawv@engadget.com",
        "employmentStatus": "Paralegal",
        "job": "Teacher",
        "creditScore": 782,
        "annualIncome": "€74342,43",
        "estimatedExpanses": "€1941,01",
        "netMonthlyIncome": "€39085,23",
        "reserves": "€244657,99"
    },
    {
        "id": 33,
        "first_name": "Lotta",
        "last_name": "Somerlie",
        "age": 66,
        "gender": "Female",
        "adress": "1 Warrior Alley",
        "adressSecondLine": "Suite 28",
        "email": "lsomerliew@usnews.com",
        "phone": "+967 564 531 6312",
        "notes": "lsomerliew@blogger.com",
        "employmentStatus": "Compensation Analyst",
        "job": "Senior Developer",
        "creditScore": 827,
        "annualIncome": "€87743,23",
        "estimatedExpanses": "€2181,69",
        "netMonthlyIncome": "€6677,15",
        "reserves": "€198550,06"
    },
    {
        "id": 34,
        "first_name": "Jehu",
        "last_name": "Maiklem",
        "age": 68,
        "gender": "Male",
        "adress": "11287 Sachs Terrace",
        "adressSecondLine": "Room 618",
        "email": "jmaiklemx@tinypic.com",
        "phone": "+86 683 138 4743",
        "notes": "jmaiklemx@ameblo.jp",
        "employmentStatus": "Environmental Specialist",
        "job": "Graphic Designer",
        "creditScore": 389,
        "annualIncome": "€77990,98",
        "estimatedExpanses": "€2186,43",
        "netMonthlyIncome": "€46770,29",
        "reserves": "€203095,50"
    },
    {
        "id": 35,
        "first_name": "Sanford",
        "last_name": "Ovell",
        "age": 61,
        "gender": "Male",
        "adress": "19 Killdeer Way",
        "adressSecondLine": "Suite 70",
        "email": "sovelly@webeden.co.uk",
        "phone": "+970 573 858 5460",
        "notes": "sovelly@istockphoto.com",
        "employmentStatus": "Safety Technician I",
        "job": "Engineer II",
        "creditScore": 444,
        "annualIncome": "€70026,39",
        "estimatedExpanses": "€2119,51",
        "netMonthlyIncome": "€50506,30",
        "reserves": "€139116,17"
    },
    {
        "id": 36,
        "first_name": "Karylin",
        "last_name": "Leither",
        "age": 47,
        "gender": "Female",
        "adress": "7 Oxford Street",
        "adressSecondLine": "Room 1948",
        "email": "kleitherz@dedecms.com",
        "phone": "+380 111 782 6183",
        "notes": "kleitherz@issuu.com",
        "employmentStatus": "Human Resources Assistant II",
        "job": "Nurse Practicioner",
        "creditScore": 884,
        "annualIncome": "€60065,62",
        "estimatedExpanses": "€2923,43",
        "netMonthlyIncome": "€31993,52",
        "reserves": "€286768,78"
    },
    {
        "id": 37,
        "first_name": "Currie",
        "last_name": "Belford",
        "age": 29,
        "gender": "Male",
        "adress": "47 Monterey Center",
        "adressSecondLine": "Suite 9",
        "email": "cbelford10@issuu.com",
        "phone": "+389 865 322 8048",
        "notes": "cbelford10@statcounter.com",
        "employmentStatus": "Mechanical Systems Engineer",
        "job": "Dental Hygienist",
        "creditScore": 829,
        "annualIncome": "€103315,62",
        "estimatedExpanses": "€3729,09",
        "netMonthlyIncome": "€1099,42",
        "reserves": "€286387,74"
    },
    {
        "id": 38,
        "first_name": "Lennard",
        "last_name": "Deignan",
        "age": 24,
        "gender": "Male",
        "adress": "64606 Manufacturers Terrace",
        "adressSecondLine": "PO Box 29178",
        "email": "ldeignan11@guardian.co.uk",
        "phone": "+420 895 704 9749",
        "notes": "ldeignan11@mozilla.org",
        "employmentStatus": "Nuclear Power Engineer",
        "job": "Marketing Manager",
        "creditScore": 753,
        "annualIncome": "€97721,87",
        "estimatedExpanses": "€2669,55",
        "netMonthlyIncome": "€32203,71",
        "reserves": "€241986,18"
    },
    {
        "id": 39,
        "first_name": "Kalinda",
        "last_name": "Abbatini",
        "age": 21,
        "gender": "Female",
        "adress": "73 Susan Avenue",
        "adressSecondLine": "20th Floor",
        "email": "kabbatini12@drupal.org",
        "phone": "+370 759 541 3752",
        "notes": "kabbatini12@gmpg.org",
        "employmentStatus": "Cost Accountant",
        "job": "Senior Sales Associate",
        "creditScore": 699,
        "annualIncome": "€71789,73",
        "estimatedExpanses": "€3780,59",
        "netMonthlyIncome": "€1845,89",
        "reserves": "€201778,43"
    },
    {
        "id": 40,
        "first_name": "Luce",
        "last_name": "Mation",
        "age": 25,
        "gender": "Male",
        "adress": "776 Macpherson Crossing",
        "adressSecondLine": "Suite 29",
        "email": "lmation13@smh.com.au",
        "phone": "+234 250 654 1176",
        "notes": "lmation13@gnu.org",
        "employmentStatus": "Environmental Specialist",
        "job": "Automation Specialist III",
        "creditScore": 367,
        "annualIncome": "€71190,64",
        "estimatedExpanses": "€3333,64",
        "netMonthlyIncome": "€25350,60",
        "reserves": "€181902,39"
    },
    {
        "id": 41,
        "first_name": "Natty",
        "last_name": "Rigler",
        "age": 65,
        "gender": "Male",
        "adress": "2 Petterle Street",
        "adressSecondLine": "Room 4",
        "email": "nrigler14@bbc.co.uk",
        "phone": "+93 977 195 8340",
        "notes": "nrigler14@sogou.com",
        "employmentStatus": "Administrative Officer",
        "job": "Analyst Programmer",
        "creditScore": 795,
        "annualIncome": "€84417,06",
        "estimatedExpanses": "€3077,09",
        "netMonthlyIncome": "€32225,53",
        "reserves": "€91394,09"
    },
    {
        "id": 42,
        "first_name": "Thaddus",
        "last_name": "Bartolomeoni",
        "age": 40,
        "gender": "Male",
        "adress": "9 Fair Oaks Pass",
        "adressSecondLine": "PO Box 10774",
        "email": "tbartolomeoni15@miitbeian.gov.cn",
        "phone": "+86 623 352 6864",
        "notes": "tbartolomeoni15@psu.edu",
        "employmentStatus": "Automation Specialist IV",
        "job": "Assistant Professor",
        "creditScore": 506,
        "annualIncome": "€102018,46",
        "estimatedExpanses": "€2119,75",
        "netMonthlyIncome": "€71999,12",
        "reserves": "€28374,60"
    },
    {
        "id": 43,
        "first_name": "Tarra",
        "last_name": "Flounders",
        "age": 43,
        "gender": "Female",
        "adress": "78801 Armistice Drive",
        "adressSecondLine": "Suite 10",
        "email": "tflounders16@pbs.org",
        "phone": "+33 828 506 5178",
        "notes": "tflounders16@wordpress.org",
        "employmentStatus": "Developer I",
        "job": "Paralegal",
        "creditScore": 407,
        "annualIncome": "€36919,48",
        "estimatedExpanses": "€3030,73",
        "netMonthlyIncome": "€20279,75",
        "reserves": "€229576,63"
    },
    {
        "id": 44,
        "first_name": "Claudette",
        "last_name": "Pridham",
        "age": 70,
        "gender": "Female",
        "adress": "01 Troy Pass",
        "adressSecondLine": "Apt 345",
        "email": "cpridham17@jimdo.com",
        "phone": "+1 915 347 8222",
        "notes": "cpridham17@123-reg.co.uk",
        "employmentStatus": "Assistant Manager",
        "job": "Computer Systems Analyst III",
        "creditScore": 402,
        "annualIncome": "€60954,56",
        "estimatedExpanses": "€1642,85",
        "netMonthlyIncome": "€47659,40",
        "reserves": "€37134,36"
    },
    {
        "id": 45,
        "first_name": "Maurizia",
        "last_name": "Alden",
        "age": 56,
        "gender": "Female",
        "adress": "097 Elmside Way",
        "adressSecondLine": "Apt 502",
        "email": "malden18@ca.gov",
        "phone": "+86 330 882 2787",
        "notes": "malden18@oakley.com",
        "employmentStatus": "Nuclear Power Engineer",
        "job": "Compensation Analyst",
        "creditScore": 482,
        "annualIncome": "€103463,45",
        "estimatedExpanses": "€2375,28",
        "netMonthlyIncome": "€20437,19",
        "reserves": "€118042,02"
    },
    {
        "id": 46,
        "first_name": "Laurent",
        "last_name": "Barnsdale",
        "age": 28,
        "gender": "Male",
        "adress": "361 Bobwhite Way",
        "adressSecondLine": "Room 740",
        "email": "lbarnsdale19@flavors.me",
        "phone": "+86 805 773 6971",
        "notes": "lbarnsdale19@telegraph.co.uk",
        "employmentStatus": "Nuclear Power Engineer",
        "job": "Research Nurse",
        "creditScore": 334,
        "annualIncome": "€37747,58",
        "estimatedExpanses": "€2729,26",
        "netMonthlyIncome": "€35140,07",
        "reserves": "€59727,91"
    },
    {
        "id": 47,
        "first_name": "Hayward",
        "last_name": "Wordington",
        "age": 43,
        "gender": "Male",
        "adress": "8 Corben Court",
        "adressSecondLine": "PO Box 6331",
        "email": "hwordington1a@uiuc.edu",
        "phone": "+385 970 784 2436",
        "notes": "hwordington1a@delicious.com",
        "employmentStatus": "Teacher",
        "job": "Graphic Designer",
        "creditScore": 451,
        "annualIncome": "€66009,24",
        "estimatedExpanses": "€2474,90",
        "netMonthlyIncome": "€8592,53",
        "reserves": "€133239,50"
    },
    {
        "id": 48,
        "first_name": "Mada",
        "last_name": "Biglin",
        "age": 28,
        "gender": "Female",
        "adress": "38038 Fairfield Point",
        "adressSecondLine": "8th Floor",
        "email": "mbiglin1b@nhs.uk",
        "phone": "+269 120 900 2987",
        "notes": "mbiglin1b@webnode.com",
        "employmentStatus": "Account Executive",
        "job": "Web Developer II",
        "creditScore": 537,
        "annualIncome": "€84987,25",
        "estimatedExpanses": "€2701,16",
        "netMonthlyIncome": "€51766,13",
        "reserves": "€22327,54"
    },
    {
        "id": 49,
        "first_name": "Johna",
        "last_name": "Grout",
        "age": 46,
        "gender": "Female",
        "adress": "039 Norway Maple Lane",
        "adressSecondLine": "Room 1018",
        "email": "jgrout1c@joomla.org",
        "phone": "+51 804 272 9557",
        "notes": "jgrout1c@mac.com",
        "employmentStatus": "Research Associate",
        "job": "Assistant Professor",
        "creditScore": 756,
        "annualIncome": "€75411,07",
        "estimatedExpanses": "€2977,00",
        "netMonthlyIncome": "€36067,50",
        "reserves": "€290044,89"
    },
    {
        "id": 50,
        "first_name": "Stephie",
        "last_name": "Tonner",
        "age": 53,
        "gender": "Female",
        "adress": "3280 Springview Plaza",
        "adressSecondLine": "Room 1103",
        "email": "stonner1d@state.tx.us",
        "phone": "+62 322 647 2065",
        "notes": "stonner1d@51.la",
        "employmentStatus": "Sales Representative",
        "job": "Environmental Specialist",
        "creditScore": 884,
        "annualIncome": "€28217,21",
        "estimatedExpanses": "€2361,08",
        "netMonthlyIncome": "€38157,93",
        "reserves": "€251441,58"
    }
]